ircmsgfmt
