Metadata-Version: 1.0
Name: ircmsgfmt
Version: 0.0.2.post3
Summary: A formatter for IRC network log
Home-page: UNKNOWN
Author: OriginCode
Author-email: origincoder@yahoo.com
License: GPLv3
Keywords: IRC format formatter
Platform: UNKNOWN
